<?xml version="1.0" encoding="UTF-8"?>
<metadata xml:lang="en"><Esri><CreaDate>20220602</CreaDate><CreaTime>13471400</CreaTime><ArcGISFormat>1.0</ArcGISFormat><SyncOnce>TRUE</SyncOnce><DataProperties><itemProps><itemLocation><linkage Sync="TRUE">file://\\142.1.121.200\dev$\Publishing\DLI_2021\DLI_2021_Census_CBF_Eng_Nat_da\data\lda_000b21a_e</linkage><protocol Sync="TRUE">Local Area Network</protocol></itemLocation></itemProps><copyHistory><copy source="\\142.1.121.200\dev$\Data_for_Loading\DLI\2021\CartographicBoundaryFiles_CBF\Eng\Shapefiles\lda_000b21a_e\lda_000b21a_e" dest="\\142.1.121.200\dev$\Publishing\DLI_2021\DLI_2021_Census_CBF_Eng_Nat_da\data\lda_000b21a_e" date="20220602" time="13471400"></copy></copyHistory></DataProperties></Esri></metadata>
